sesame/__init__.py
sesame/_version.py
sesame/analyzer.py
sesame/builder.py
sesame/defects.py
sesame/getF.py
sesame/getFandJ_eq.py
sesame/jacobian.py
sesame/observables.py
sesame/plotter.py
sesame/solvers.py
sesame/utils.py
solsesame-2.0.dist-info/AUTHORS.rst
solsesame-2.0.dist-info/LICENSE.rst
solsesame-2.0.dist-info/METADATA
solsesame-2.0.dist-info/WHEEL
solsesame-2.0.dist-info/top_level.txt
solsesame-2.0.dist-info/RECORD
